Metadata-Version: 2.1
Name: dxfstructure
Version: 0.4.8
Summary: Structural engineering dxf drawing system
Home-page: https://bitbucket.org/lukaszlaba/dxfstructure
Author: Lukasz Laba
Author-email: lukaszlaba@gmail.com
License: GNU General Public License (GPL)
Keywords: civil engineering,structural engineering,concrete structures,steel structures
Classifier: Development Status :: 3 - Alpha
Classifier: Environment :: X11 Applications :: Qt
Classifier: Intended Audience :: End Users/Desktop
Classifier: License :: OSI Approved :: GNU General Public License (GPL)
Classifier: Operating System :: POSIX :: Linux
Classifier: Operating System :: Microsoft :: Windows
Classifier: Programming Language :: Python
Classifier: Topic :: Scientific/Engineering
Requires-Python: >=3.5, <4
